atommap_eval/__init__.py
atommap_eval/cli.py
atommap_eval/data_models.py
atommap_eval/evaluator.py
atommap_eval/input_io.py
atommap_eval/pair_evaluation.py
atommap_eval/preprocess.py
atommap_eval/rxn_graph.py
atommap_eval/rxnmapper_utils.py
atommap_eval-1.4.0.dist-info/licenses/LICENSE
atommap_eval-1.4.0.dist-info/METADATA
atommap_eval-1.4.0.dist-info/WHEEL
atommap_eval-1.4.0.dist-info/entry_points.txt
atommap_eval-1.4.0.dist-info/top_level.txt
atommap_eval-1.4.0.dist-info/RECORD
