Metadata-Version: 2.4
Name: atommap-eval
Version: 1.4.0
Summary: Evaluate atom-mapping equivalence of chemical reactions using graph isomorphism.
Author-email: Yves Grandjean <yves.grandjean@unibe.ch>
License: MIT License
Requires-Python: >=3.8
License-File: LICENSE
Requires-Dist: rdkit
Requires-Dist: networkx>=2.8
Requires-Dist: pandas>=1.3
Requires-Dist: rxn-utils
Requires-Dist: rxn-chem-utils
Requires-Dist: wrapt_timeout_decorator
Provides-Extra: dev
Requires-Dist: pytest; extra == "dev"
Requires-Dist: pytest-cov; extra == "dev"
Requires-Dist: black; extra == "dev"
Requires-Dist: ruff; extra == "dev"
Dynamic: license-file
